{
    "sections": {
        "ss_hero_pro_9MLPnz": {
            "type": "ss-hero-pro",
            "blocks": {
                "caption_QCbqWE": {
                    "type": "caption",
                    "settings": {
                        "caption": "<h3>WÄHLE DEINE SPIELKATEGORIE<\/h3>",
                        "caption_custom": false,
                        "caption_font": "josefin_sans_n4",
                        "caption_size": 12,
                        "caption_size_mobile": 12,
                        "caption_advanced": false,
                        "caption_height": 130,
                        "caption_mt": 0,
                        "caption_mt_mobile": 0,
                        "background": false,
                        "caption_bg_opacity": 0.3,
                        "enable_blur": true,
                        "caption_radius": 100,
                        "caption_border_thickness": 1,
                        "caption_padding_horizontal": 12,
                        "caption_padding_horizontal_mobile": 12,
                        "caption_padding_vertical": 6,
                        "caption_padding_vertical_mobile": 6,
                        "caption_color": "#a1d9ee",
                        "caption_bg_color": "#ffffff",
                        "caption_border_color": "#ffffff"
                    }
                },
                "heading_JzFph8": {
                    "type": "heading",
                    "settings": {
                        "heading": "<h1>Welcher Typ Abenteurer bist du?<\/h1>",
                        "heading_custom": false,
                        "heading_font": "josefin_sans_n4",
                        "heading_accent_font": "playfair_n4",
                        "heading_size": 56,
                        "heading_size_mobile": 36,
                        "heading_advanced": false,
                        "heading_height": 130,
                        "heading_mt": 8,
                        "heading_mt_mobile": 8,
                        "heading_color": "#f9f544",
                        "heading_accent_color": "#afafaf"
                    }
                },
                "text_YJdyxx": {
                    "type": "text",
                    "settings": {
                        "text": "<p>Entscheide dich zwischen Gastro und City Escape Game.<\/p>",
                        "text_custom": false,
                        "text_font": "josefin_sans_n4",
                        "text_size": 18,
                        "text_size_mobile": 14,
                        "text_advanced": false,
                        "text_height": 150,
                        "text_mt": 20,
                        "text_mt_mobile": 20,
                        "text_color": "#ffffff"
                    }
                },
                "review_REMiK7": {
                    "type": "review",
                    "settings": {
                        "stars_count": 4.5,
                        "stars_icon": "shopify:\/\/shop_images\/Stern-Bewertung.png",
                        "stars_size": 16,
                        "stars_size_mobile": 14,
                        "stars_gap": 2,
                        "review": "<p>4.8 Sterne | 25.000+ Spieler<\/p>",
                        "review_custom": false,
                        "review_font": "josefin_sans_n4",
                        "review_size": 14,
                        "review_size_mobile": 12,
                        "review_height": 130,
                        "background": true,
                        "review_bg_opacity": 0.3,
                        "enable_blur": true,
                        "review_radius": 10,
                        "review_border_thickness": 1,
                        "review_mt": 12,
                        "review_mt_mobile": 12,
                        "review_padding_horizontal": 12,
                        "review_padding_horizontal_mobile": 12,
                        "review_padding_vertical": 8,
                        "review_padding_vertical_mobile": 8,
                        "review_color": "#ffffff",
                        "review_bg_color": "#ffffff",
                        "review_border_color": "#ffffff",
                        "stars_color": "#ffffff",
                        "stars_bg_color": "#00b67a",
                        "stars_bg_half_color": "#dddddd"
                    }
                },
                "feature_xM3mti": {
                    "type": "feature",
                    "settings": {
                        "icon": "rocket",
                        "text": "27 Spiele"
                    }
                },
                "feature_pz6NXV": {
                    "type": "feature",
                    "settings": {
                        "icon": "sliders",
                        "text": "2 Spielkategorien"
                    }
                },
                "feature_Qx63wm": {
                    "type": "feature",
                    "settings": {
                        "icon": "heart_hand",
                        "text": "auch Spiele für Kinder ab 6 Jahren"
                    }
                },
                "button_LR8KyE": {
                    "type": "button",
                    "settings": {
                        "button": "Spiel wählen",
                        "url": "",
                        "open_in_new_tab": false,
                        "button_style": "non_outline",
                        "button_custom": false,
                        "button_font": "josefin_sans_n4",
                        "button_size": 14,
                        "button_size_mobile": 14,
                        "button_advanced": false,
                        "button_height": 100,
                        "button_padding_horizontal": 40,
                        "button_padding_horizontal_mobile": 32,
                        "button_padding_vertical": 20,
                        "button_padding_vertical_mobile": 20,
                        "button_radius": 100,
                        "button_border_thickness": 1,
                        "button_mt": 24,
                        "button_mt_mobile": 24,
                        "button_custom_styling": true,
                        "button_full_width_mobile": true,
                        "button_color": "#1f1f21",
                        "button_hover_color": "#ffffff",
                        "button_bg_color": "#f9f544",
                        "button_bg_hover_color": "#2d2d2d",
                        "button_border_color": "#1a1a1a",
                        "button_border_hover_color": "#1a1a1a",
                        "button_shadow_color": "#000000"
                    }
                }
            },
            "block_order": [
                "caption_QCbqWE",
                "heading_JzFph8",
                "text_YJdyxx",
                "review_REMiK7",
                "feature_xM3mti",
                "feature_pz6NXV",
                "feature_Qx63wm",
                "button_LR8KyE"
            ],
            "name": "SS - Hero pro 💎",
            "settings": {
                "hero_height": "full_screen",
                "hero_fixed_height": 600,
                "hero_fixed_height_mobile": 600,
                "content_max_width": 41,
                "enable_split_layout": false,
                "content_align": "left",
                "content_align_mobile": "left",
                "content_vertical_align": "center",
                "content_vertical_align_mobile": "end",
                "features_advanced": false,
                "features_mt": 20,
                "features_mt_mobile": 20,
                "features_gap": 24,
                "features_gap_mobile": 12,
                "feature_background": false,
                "feature_bg_opacity": 0.3,
                "feature_enable_blur": true,
                "feature_radius": 100,
                "feature_border_thickness": 1,
                "feature_padding_horizontal": 12,
                "feature_padding_horizontal_mobile": 12,
                "feature_padding_vertical": 6,
                "feature_padding_vertical_mobile": 6,
                "feature_icon_size": 18,
                "feature_icon_size_mobile": 16,
                "feature_text_custom": false,
                "feature_text_font": "josefin_sans_n4",
                "feature_text_size": 16,
                "feature_text_size_mobile": 14,
                "feature_text_height": 150,
                "feature_icon_color": "#ffffff",
                "feature_text_color": "#ffffff",
                "feature_bg_color": "#ffffff",
                "feature_border_color": "#ffffff",
                "layout_bg_type": "image",
                "bg_video_url": "",
                "bg_overlay": 0.2,
                "bg_overlay_color": "#121212",
                "background_style": "solid",
                "background_color": "#121212",
                "background_gradient": "radial-gradient(rgba(30, 30, 36, 1), rgba(5, 5, 5, 1) 100%)",
                "border_color": "#121212",
                "margin_top": 0,
                "margin_bottom": 0,
                "margin_horizontal": 0,
                "margin_horizontal_mobile": 0,
                "padding_top": 16,
                "padding_bottom": 36,
                "padding_horizontal": 5,
                "padding_horizontal_mobile": 1.5,
                "width": "custom",
                "content_width": 1200,
                "border_thickness": 0,
                "section_radius": 0,
                "lazy": false
            }
        },
        "main": {
            "type": "main-list-collections",
            "disabled": true,
            "settings": {
                "title": "Story World",
                "sort": "products_high",
                "image_ratio": "portrait",
                "columns_desktop": 4,
                "columns_mobile": "2"
            }
        },
        "featured_collection_f9dV6U": {
            "type": "featured-collection",
            "settings": {
                "collection": "gastro-escape-games",
                "products_to_show": 4,
                "title": "Vergiss normales Bar-Hopping – Dein Abend hat eine Mission.",
                "heading_size": "h2",
                "description": "<p>Unsere Gastro Escape Games<\/p>",
                "show_description": false,
                "description_style": "uppercase",
                "columns_desktop": 4,
                "enable_desktop_slider": false,
                "full_width": false,
                "show_view_all": true,
                "view_all_style": "solid",
                "color_scheme": "background-1",
                "image_ratio": "square",
                "image_shape": "default",
                "show_secondary_image": false,
                "show_vendor": false,
                "show_rating": false,
                "quick_add": "standard",
                "columns_mobile": "2",
                "swipe_on_mobile": false,
                "padding_top": 36,
                "padding_bottom": 36
            }
        },
        "featured_collection_EnEcTG": {
            "type": "featured-collection",
            "settings": {
                "collection": "escape-games",
                "products_to_show": 4,
                "title": "Deine Stadt ist das Rätsel - Findest du die Lösung?",
                "heading_size": "h2",
                "description": "<p>Unsere City Escape Games<\/p>",
                "show_description": false,
                "description_style": "uppercase",
                "columns_desktop": 4,
                "enable_desktop_slider": false,
                "full_width": false,
                "show_view_all": true,
                "view_all_style": "solid",
                "color_scheme": "",
                "image_ratio": "square",
                "image_shape": "default",
                "show_secondary_image": false,
                "show_vendor": false,
                "show_rating": false,
                "quick_add": "standard",
                "columns_mobile": "2",
                "swipe_on_mobile": false,
                "padding_top": 36,
                "padding_bottom": 36
            }
        },
        "featured_collection_8zzY8K": {
            "type": "featured-collection",
            "disabled": true,
            "settings": {
                "collection": "special-events",
                "products_to_show": 4,
                "title": "Special Events",
                "heading_size": "h1",
                "description": "",
                "show_description": false,
                "description_style": "body",
                "columns_desktop": 4,
                "enable_desktop_slider": false,
                "full_width": false,
                "show_view_all": true,
                "view_all_style": "solid",
                "color_scheme": "",
                "image_ratio": "adapt",
                "image_shape": "default",
                "show_secondary_image": false,
                "show_vendor": false,
                "show_rating": false,
                "quick_add": "none",
                "columns_mobile": "2",
                "swipe_on_mobile": false,
                "padding_top": 36,
                "padding_bottom": 36
            }
        },
        "featured_collection_AqDfGD": {
            "type": "featured-collection",
            "settings": {
                "collection": "gutschein",
                "products_to_show": 2,
                "title": "Gemeinsame Zeit ist das Schönste - Verschenke ein Abenteuer!",
                "heading_size": "h2",
                "description": "<p>Unsere Geschenkgutscheine<\/p>",
                "show_description": false,
                "description_style": "uppercase",
                "columns_desktop": 4,
                "enable_desktop_slider": false,
                "full_width": false,
                "show_view_all": true,
                "view_all_style": "solid",
                "color_scheme": "",
                "image_ratio": "adapt",
                "image_shape": "default",
                "show_secondary_image": false,
                "show_vendor": false,
                "show_rating": false,
                "quick_add": "standard",
                "columns_mobile": "2",
                "swipe_on_mobile": false,
                "padding_top": 36,
                "padding_bottom": 36
            }
        },
        "ss_hero_pro_KeYa76": {
            "type": "ss-hero-pro",
            "blocks": {
                "caption_DCD3Wf": {
                    "type": "caption",
                    "settings": {
                        "caption": "<p>FÜR UNTERNEHMEN<\/p>",
                        "caption_custom": false,
                        "caption_font": "josefin_sans_n4",
                        "caption_size": 12,
                        "caption_size_mobile": 12,
                        "caption_advanced": false,
                        "caption_height": 130,
                        "caption_mt": 0,
                        "caption_mt_mobile": 0,
                        "background": false,
                        "caption_bg_opacity": 0.3,
                        "enable_blur": true,
                        "caption_radius": 100,
                        "caption_border_thickness": 1,
                        "caption_padding_horizontal": 12,
                        "caption_padding_horizontal_mobile": 12,
                        "caption_padding_vertical": 6,
                        "caption_padding_vertical_mobile": 6,
                        "caption_color": "#f9f544",
                        "caption_bg_color": "#ffffff",
                        "caption_border_color": "#ffffff"
                    }
                },
                "heading_WmrRBx": {
                    "type": "heading",
                    "settings": {
                        "heading": "<h2>Teambuilding, das wirklich Spaß macht.<\/h2>",
                        "heading_custom": false,
                        "heading_font": "josefin_sans_n4",
                        "heading_accent_font": "playfair_n4",
                        "heading_size": 56,
                        "heading_size_mobile": 36,
                        "heading_advanced": false,
                        "heading_height": 130,
                        "heading_mt": 8,
                        "heading_mt_mobile": 8,
                        "heading_color": "#ffffff",
                        "heading_accent_color": "#f9f544"
                    }
                },
                "text_dtHRQE": {
                    "type": "text",
                    "settings": {
                        "text": "<p>Escape Games als Teamevent — unkompliziert, flexibel und garantiert kein langweiliger Workshop. Perfekt für Teams ab 4 Personen. Individuelle Pakete auf Anfrage.<\/p>",
                        "text_custom": false,
                        "text_font": "josefin_sans_n4",
                        "text_size": 18,
                        "text_size_mobile": 14,
                        "text_advanced": false,
                        "text_height": 150,
                        "text_mt": 20,
                        "text_mt_mobile": 20,
                        "text_color": "#ffffff"
                    }
                },
                "feature_HQ4YXq": {
                    "type": "feature",
                    "settings": {
                        "icon": "scallop_checkmark",
                        "text": "Minimaler Aufwand"
                    }
                },
                "feature_zwb8RW": {
                    "type": "feature",
                    "settings": {
                        "icon": "headset",
                        "text": "Individuelle Beratung"
                    }
                },
                "feature_i3t6eb": {
                    "type": "feature",
                    "settings": {
                        "icon": "award",
                        "text": "98%Weiterempfehlung"
                    }
                },
                "button_4xFbaG": {
                    "type": "button",
                    "settings": {
                        "button": "Mehr erfahren",
                        "url": "shopify:\/\/pages\/unternehmen",
                        "open_in_new_tab": false,
                        "button_style": "non_outline",
                        "button_custom": false,
                        "button_font": "josefin_sans_n4",
                        "button_size": 14,
                        "button_size_mobile": 14,
                        "button_advanced": false,
                        "button_height": 100,
                        "button_padding_horizontal": 40,
                        "button_padding_horizontal_mobile": 32,
                        "button_padding_vertical": 20,
                        "button_padding_vertical_mobile": 20,
                        "button_radius": 100,
                        "button_border_thickness": 1,
                        "button_mt": 24,
                        "button_mt_mobile": 24,
                        "button_custom_styling": true,
                        "button_full_width_mobile": true,
                        "button_color": "#1f1f21",
                        "button_hover_color": "#ffffff",
                        "button_bg_color": "#f9f544",
                        "button_bg_hover_color": "#2d2d2d",
                        "button_border_color": "#1a1a1a",
                        "button_border_hover_color": "#1a1a1a",
                        "button_shadow_color": "#000000"
                    }
                }
            },
            "block_order": [
                "caption_DCD3Wf",
                "heading_WmrRBx",
                "text_dtHRQE",
                "feature_HQ4YXq",
                "feature_zwb8RW",
                "feature_i3t6eb",
                "button_4xFbaG"
            ],
            "name": "SS - Hero pro 💎",
            "settings": {
                "hero_height": "fixed_height",
                "hero_fixed_height": 390,
                "hero_fixed_height_mobile": 600,
                "content_max_width": 100,
                "enable_split_layout": false,
                "content_align": "center",
                "content_align_mobile": "center",
                "content_vertical_align": "center",
                "content_vertical_align_mobile": "end",
                "features_advanced": false,
                "features_mt": 20,
                "features_mt_mobile": 20,
                "features_gap": 24,
                "features_gap_mobile": 12,
                "feature_background": false,
                "feature_bg_opacity": 0.3,
                "feature_enable_blur": true,
                "feature_radius": 100,
                "feature_border_thickness": 1,
                "feature_padding_horizontal": 12,
                "feature_padding_horizontal_mobile": 12,
                "feature_padding_vertical": 6,
                "feature_padding_vertical_mobile": 6,
                "feature_icon_size": 18,
                "feature_icon_size_mobile": 16,
                "feature_text_custom": false,
                "feature_text_font": "josefin_sans_n4",
                "feature_text_size": 16,
                "feature_text_size_mobile": 14,
                "feature_text_height": 150,
                "feature_icon_color": "#fafafa",
                "feature_text_color": "#fafafa",
                "feature_bg_color": "#ffffff",
                "feature_border_color": "#ffffff",
                "layout_bg_type": "color",
                "bg_video_url": "",
                "bg_overlay": 0.2,
                "bg_overlay_color": "#121212",
                "background_style": "solid",
                "background_color": "#a1d9ee",
                "background_gradient": "radial-gradient(rgba(30, 30, 36, 1), rgba(5, 5, 5, 1) 100%)",
                "border_color": "#191919",
                "margin_top": 0,
                "margin_bottom": 0,
                "margin_horizontal": 0,
                "margin_horizontal_mobile": 0,
                "padding_top": 36,
                "padding_bottom": 36,
                "padding_horizontal": 5,
                "padding_horizontal_mobile": 1.5,
                "width": "page",
                "content_width": 1200,
                "border_thickness": 3,
                "section_radius": 0,
                "lazy": false
            }
        }
    },
    "order": [
        "ss_hero_pro_9MLPnz",
        "main",
        "featured_collection_f9dV6U",
        "featured_collection_EnEcTG",
        "featured_collection_8zzY8K",
        "featured_collection_AqDfGD",
        "ss_hero_pro_KeYa76"
    ]
}